caped_ai_mtrack/Fits.png
caped_ai_mtrack/Fits_linear_linear.png
caped_ai_mtrack/Fits_quadratic_linear.png
caped_ai_mtrack/__init__.py
caped_ai_mtrack/_tests.png
caped_ai_mtrack/_testsGT.png
caped_ai_mtrack/_testsGT_quad.png
caped_ai_mtrack/_tests_linear_linear.png
caped_ai_mtrack/_tests_quadratic_linear.png
caped_ai_mtrack/_version.py
caped_ai_mtrack/caped.yaml
caped_ai_mtrack/Fits/__init__.py
caped_ai_mtrack/Fits/comboransac.py
caped_ai_mtrack/Fits/ransac.py
caped_ai_mtrack/Fits/regression.py
caped_ai_mtrack/Fits/utils.py
caped_ai_mtrack/RansacModels/__init__.py
caped_ai_mtrack/RansacModels/generalized_function.py
caped_ai_mtrack/RansacModels/linear_function.py
caped_ai_mtrack/RansacModels/polynomial_function.py
caped_ai_mtrack/RansacModels/quadratic_function.py
caped_ai_mtrack/Solvers/__init__.py
caped_ai_mtrack/Solvers/newton_raphson.py
caped_ai_mtrack/_tests/__init__.py
caped_ai_mtrack/_tests/test_ransac.py
caped_ai_mtrack/_tests/utils.py
caped_ai_mtrack-1.1.9.dist-info/LICENSE
caped_ai_mtrack-1.1.9.dist-info/METADATA
caped_ai_mtrack-1.1.9.dist-info/WHEEL
caped_ai_mtrack-1.1.9.dist-info/entry_points.txt
caped_ai_mtrack-1.1.9.dist-info/top_level.txt
caped_ai_mtrack-1.1.9.dist-info/RECORD
